{"api-examples.md":"CC_jFPoh","index.md":"DA8fpBY9","markdown-examples.md":"DIIxD6Y-","写在最前面_index.md":"U2ylAcE1","新的探索_chapter_00_00.md":"Dh_4RRxB","新的探索_chapter_00_01.md":"DsBMLBHc","新的探索_chapter_00_02.md":"G5yDGIBp","新的探索_chapter_00_03.md":"Ch5ceSKi","新的探索_chapter_00_04.md":"BfjD3k50","新的探索_chapter_00_05.md":"DWduUIa2","新的探索_chapter_01_00.md":"B3w_RKzy","新的探索_chapter_01_01.md":"DXC_OuW6","新的探索_chapter_01_02.md":"LYy0ldJY","新的探索_chapter_01_03.md":"_Xva6nbe","新的探索_chapter_01_04.md":"CNXuzJLF","新的探索_chapter_02_00.md":"CNjhp9Fj","新的探索_chapter_02_01.md":"DBhOxUr7","新的探索_chapter_02_02.md":"BDAsWAVx","新的探索_chapter_02_03.md":"3UV3n4MY","新的探索_chapter_02_04.md":"BVswl4X1","新的探索_chapter_02_05.md":"LL6jRZc3","新的探索_chapter_02_06.md":"Cw7FQ7D3","新的探索_chapter_02_07.md":"DA1DOeh6","新的探索_chapter_02_08.md":"DBY3xwug","杂谈_00.md":"C0czrHof","杂谈_01.md":"xOs8dK39","杂谈_02.md":"CRMuR446","杂谈_03.md":"CeMIAgc8","杂谈_05.md":"Pl0JDh5H"}
